{
  "id": "R-1C4AF1EA",
  "schema_version": "3.0.0",
  "title": "Calgary mayor, minister to discuss bike lanes",
  "outlet": "The Canadian Press",
  "outlet_id": "canadian-press",
  "section": "News",
  "author": null,
  "publication_date": null,
  "url": "https://www.thecanadianpressnews.ca/prairies_bc/alberta/calgary-mayor-alberta-minister-to-discuss-bike-lanes-as-threats-of-removal-loom/article_57886279-9b61-5067-bbc2-46bf1a86011c.html",
  "source_type": "wire_article",
  "url_status": "unverified",
  "archived_url": null,
  "tier": 2,
  "verified": false,
  "wire_source": "The Canadian Press",
  "notes": null,
  "submission_source": "manual-intake",
  "submission_status": "pending"
}
