{
  "id": "R-38E5ED28",
  "schema_version": "3.0.0",
  "title": "Premier on immigration",
  "outlet": "National Post",
  "outlet_id": "national-post",
  "section": "News",
  "author": null,
  "publication_date": null,
  "url": "https://nationalpost.com/news/canada/alberta-immigration-danielle-smith",
  "source_type": "url_article",
  "url_status": "unverified",
  "archived_url": null,
  "tier": 2,
  "verified": false,
  "wire_source": null,
  "notes": null,
  "submission_source": "manual-intake",
  "submission_status": "pending"
}
